[
 {
  "table":"TADIR",
  "data":
  [
   {
    "PGMID":"R3TR",
    "OBJECT":"SUSH",
    "OBJ_NAME":"71A1092B84587E0A5388090E03866DHT",
    "KORRNUM":"",
    "SRCSYSTEM":"...",
    "AUTHOR":"SAP_CUSTOMER",
    "SRCDEP":"",
    "DEVCLASS":"Z_PRODUCE",
    "GENFLAG":"",
    "EDTFLAG":"",
    "CPROJECT":" L",
    "MASTERLANG":"E",
    "VERSID":"",
    "PAKNOCHECK":"",
    "OBJSTABLTY":"",
    "COMPONENT":"",
    "CRELEASE":"",
    "DELFLAG":"",
    "TRANSLTTXT":"",
    "CREATED_ON":"2024-10-16",
    "CHECK_DATE":"2024-10-16",
    "CHECK_CFG":""
   }
  ]
 },
 {
  "table":"USOBHASH",
  "data":
  [
   {
    "NAME":"71A1092B84587E0A5388090E03866D",
    "TYPE":"HT",
    "PGMID":"R3TR",
    "OBJECT":"IWSG",
    "OBJ_NAME":"ZPR_SB_RESULTS_H_0001",
    "SERVICE_TYPE":"",
    "SERVICE":""
   }
  ]
 },
 {
  "table":"USOBX",
  "data":
  [
   {
    "NAME":"71A1092B84587E0A5388090E03866D",
    "TYPE":"HT",
    "OBJECT":"S_SERVICE",
    "MODIFIER":"SAP_CUSTOMER",
    "MODDATE":"2024-10-16",
    "MODTIME":"06:50:46",
    "OKFLAG":"X"
   }
  ]
 },
 {
  "table":"USOB_SM",
  "data":
  [
   {
    "NAME":"71A1092B84587E0A5388090E03866D",
    "TYPE":"HT",
    "MODIFIER":"SAP_CUSTOMER",
    "MODDATE":"2024-10-16",
    "MODTIME":"06:50:46",
    "OKFLAG":"",
    "ATTRIBUTES":"",
    "ABAP_LANGUAGE_VERSION":"5"
   }
  ]
 }
]